sm_utils/__init__.py
sm_utils/sm_utils.py
sm_utils-0.2.7.dist-info/LICENSE
sm_utils-0.2.7.dist-info/METADATA
sm_utils-0.2.7.dist-info/WHEEL
sm_utils-0.2.7.dist-info/top_level.txt
sm_utils-0.2.7.dist-info/RECORD
