Metadata-Version: 2.1
Name: sm_utils
Version: 0.2.7
Summary: Utility Scripts
Author-email: Scott McLean <smclean@databankimx.com>
Classifier: Programming Language :: Python :: 3
Classifier: License :: OSI Approved :: MIT License
Classifier: Operating System :: OS Independent
Requires-Python: >=3.10
License-File: LICENSE
